setup.py
raspi_servo/__init__.py
raspi_servo/servo.py
raspi_servo.egg-info/PKG-INFO
raspi_servo.egg-info/SOURCES.txt
raspi_servo.egg-info/dependency_links.txt
raspi_servo.egg-info/top_level.txt