Metadata-Version: 1.0
Name: raspi-servo
Version: 1.0.5
Summary: raspi-servo
Home-page: https://github.com/weidacn/raspi-servo
Author: AW
Author-email: weidacn@qq.com
License: Public domain
Keywords: pip,raspi-servo,servo
Platform: any
